[
  {
    "blockId": "ast-icon-1",
    "kind": "icon",
    "query": "lifebuoy",
    "pack": "tabler",
    "required": true
  },
  {
    "blockId": "ast-icon-2",
    "kind": "icon",
    "query": "heart-filled",
    "pack": "tabler",
    "required": true
  },
  {
    "blockId": "ast-image-1",
    "kind": "image",
    "query": "hands holding colorful wellness supplement drop bottles pink green yellow product photography",
    "targetWidth": 600,
    "required": true
  },
  {
    "blockId": "ast-icon-3",
    "kind": "icon",
    "query": "lifebuoy",
    "pack": "tabler",
    "required": true
  },
  {
    "blockId": "ast-icon-4",
    "kind": "icon",
    "query": "brand-instagram",
    "pack": "tabler",
    "required": true
  },
  {
    "blockId": "ast-icon-5",
    "kind": "icon",
    "query": "brand-tiktok",
    "pack": "tabler",
    "required": true
  }
]
